restartprocwithvars/README.MD
restartprocwithvars/__init__.py
restartprocwithvars/requirements.txt
restartprocwithvars/thirdparty.json
restartprocwithvars-0.10.dist-info/LICENSE.rst
restartprocwithvars-0.10.dist-info/METADATA
restartprocwithvars-0.10.dist-info/WHEEL
restartprocwithvars-0.10.dist-info/top_level.txt
restartprocwithvars-0.10.dist-info/RECORD
