Metadata-Version: 2.1
Name: restartprocwithvars
Version: 0.10
Summary: Restarts process (Windows only)
Home-page: https://github.com/hansalemaos/restartprocwithvars
Author: Johannes Fischer
Author-email: aulasparticularesdealemaosp@gmail.com
License: MIT
Keywords: restart,windows
Classifier: Development Status :: 4 - Beta
Classifier: Programming Language :: Python :: 3 :: Only
Classifier: Programming Language :: Python :: 3.10
Classifier: Topic :: Software Development :: Libraries :: Python Modules
Classifier: Topic :: Utilities
License-File: LICENSE.rst
Requires-Dist: ctrlchandler
Requires-Dist: keyboard
Requires-Dist: list-all-files-recursively-short
